Metadata-Version: 1.0
Name: edkahe-distributions
Version: 0.1
Summary: Gaussian distributions
Home-page: UNKNOWN
Author: Ediz Herkert
Author-email: ediz-h@web.de
License: UNKNOWN
Platform: UNKNOWN
